code2prompt_mcp/__init__.py
code2prompt_mcp/main.py
mseep_code2prompt_mcp-0.1.4.dist-info/METADATA
mseep_code2prompt_mcp-0.1.4.dist-info/WHEEL
mseep_code2prompt_mcp-0.1.4.dist-info/licenses/LICENSE
mseep_code2prompt_mcp-0.1.4.dist-info/RECORD
